<?xml version="1.0" encoding="UTF-8"?>
<class xmlns="http://xml.phpdox.net/src" full="Composer\Console\GithubActionError" namespace="Composer\Console" name="GithubActionError" abstract="false" final="true" start="18" end="83">
  <file path="//var/www/html/vendor/composer/composer/src/Composer/Console" file="GithubActionError.php" realpath="/var/www/html/vendor/composer/composer/src/Composer/Console/GithubActionError.php" size="2421" time="2022-04-13T14:43:00+00:00" unixtime="1649860980" sha1="d854ce5465f050b102c6be44d79481419c52ce6c" relative="ar/www/html/vendor/composer/composer/src/Composer/Console/GithubActionError.php"/>
  <member name="io" visibility="protected" static="false" line="23">
    <docblock>
      <description/>
      <var type="object">
        <type full="Composer\IO\IOInterface" namespace="Composer\IO" name="IOInterface"/>
      </var>
    </docblock>
  </member>
  <constructor name="__construct" start="25" end="28" abstract="false" final="false" static="false" visibility="public">
    <parameter name="io" byreference="false" type="object">
      <type full="Composer\IO\IOInterface" namespace="Composer\IO" name="IOInterface"/>
    </parameter>
  </constructor>
  <method name="emit" start="37" end="52" abstract="false" final="false" static="false" visibility="public">
    <docblock>
      <description/>
      <param type="string" variable="$message"/>
      <param type="object" variable="$file">
        <type full="Composer\Console\null|string" namespace="Composer\Console" name="null|string"/>
      </param>
      <param type="object" variable="$line">
        <type full="Composer\Console\null|int" namespace="Composer\Console" name="null|int"/>
      </param>
      <return type="object">
        <type full="Composer\Console\void" namespace="Composer\Console" name="void"/>
      </return>
    </docblock>
    <return type="void" nullable="false"/>
    <parameter name="message" byreference="false" type="string"/>
    <parameter name="file" byreference="false" nullable="true" type="string" default="NULL"/>
    <parameter name="line" byreference="false" nullable="true" type="int" default="NULL"/>
  </method>
  <method name="escapeData" start="58" end="66" abstract="false" final="false" static="false" visibility="private">
    <docblock>
      <description/>
      <param type="string" variable="$data"/>
      <return type="string"/>
    </docblock>
    <return type="string" nullable="false"/>
    <parameter name="data" byreference="false" type="string"/>
    <inline>
      <comment value="see https://github.com/actions/toolkit/blob/4f7fb6513a355689f69f0849edeb369a4dc81729/packages/core/src/command.ts#L80-L85" line="60"/>
    </inline>
  </method>
  <method name="escapeProperty" start="72" end="82" abstract="false" final="false" static="false" visibility="private">
    <docblock>
      <description/>
      <param type="string" variable="$property"/>
      <return type="string"/>
    </docblock>
    <return type="string" nullable="false"/>
    <parameter name="property" byreference="false" type="string"/>
    <inline>
      <comment value="see https://github.com/actions/toolkit/blob/4f7fb6513a355689f69f0849edeb369a4dc81729/packages/core/src/command.ts#L87-L94" line="74"/>
    </inline>
  </method>
</class>
