<?xml version="1.0" encoding="UTF-8"?>
<class xmlns="http://xml.phpdox.net/src" full="Fabfuel\Prophiler\Adapter\Doctrine\SQLLoggerTest" namespace="Fabfuel\Prophiler\Adapter\Doctrine" name="SQLLoggerTest" abstract="false" final="false" start="9" end="80">
  <file path="//var/www/html/vendor/fabfuel/prophiler/tests/Fabfuel/Prophiler/Adapter/Doctrine" file="SQLLoggerTest.php" realpath="/var/www/html/vendor/fabfuel/prophiler/tests/Fabfuel/Prophiler/Adapter/Doctrine/SQLLoggerTest.php" size="2665" time="2017-09-16T06:49:25+00:00" unixtime="1505544565" sha1="25b86ea9fde22a33cc051ac8cb473e02c5cbd8ca" relative="ar/www/html/vendor/fabfuel/prophiler/tests/Fabfuel/Prophiler/Adapter/Doctrine/SQLLoggerTest.php"/>
  <extends full="PHPUnit_Framework_TestCase" namespace="" name="PHPUnit_Framework_TestCase"/>
  <method name="testStart" start="17" end="39" abstract="false" final="false" static="false" visibility="public">
    <docblock>
      <description/>
      <covers value="Fabfuel\Prophiler\Adapter\Doctrine\SQLLogger::startQuery"/>
      <uses value="Fabfuel\Prophiler\Adapter\Doctrine\SQLLogger"/>
      <uses value="Fabfuel\Prophiler\Profiler"/>
      <uses value="Fabfuel\Prophiler\Adapter\AdapterAbstract"/>
    </docblock>
  </method>
  <method name="testStop" start="47" end="59" abstract="false" final="false" static="false" visibility="public">
    <docblock>
      <description/>
      <covers value="Fabfuel\Prophiler\Adapter\Doctrine\SQLLogger::stopQuery"/>
      <uses value="Fabfuel\Prophiler\Adapter\Doctrine\SQLLogger"/>
      <uses value="Fabfuel\Prophiler\Profiler"/>
      <uses value="Fabfuel\Prophiler\Adapter\AdapterAbstract"/>
    </docblock>
  </method>
  <method name="testSetAndGetCurrentBenchmark" start="68" end="79" abstract="false" final="false" static="false" visibility="public">
    <docblock>
      <description/>
      <covers value="Fabfuel\Prophiler\Adapter\Doctrine\SQLLogger::getCurrentBenchmark"/>
      <covers value="Fabfuel\Prophiler\Adapter\Doctrine\SQLLogger::setCurrentBenchmark"/>
      <uses value="Fabfuel\Prophiler\Adapter\Doctrine\SQLLogger"/>
      <uses value="Fabfuel\Prophiler\Profiler"/>
      <uses value="Fabfuel\Prophiler\Adapter\AdapterAbstract"/>
    </docblock>
  </method>
  <parent full="PHPUnit_Framework_TestCase" namespace="" name="PHPUnit_Framework_TestCase">
    <extends full="PHPUnit\Framework\TestCase" namespace="PHPUnit\Framework" name="TestCase" unresolved="true"/>
  </parent>
</class>
