<?xml version="1.0" encoding="UTF-8"?>
<class xmlns="http://xml.phpdox.net/src" full="PhpCsFixer\Documentation\ListDocumentGenerator" namespace="PhpCsFixer\Documentation" name="ListDocumentGenerator" abstract="false" final="true" start="31" end="176">
  <file path="//var/www/html/vendor/friendsofphp/php-cs-fixer/src/Documentation" file="ListDocumentGenerator.php" realpath="/var/www/html/vendor/friendsofphp/php-cs-fixer/src/Documentation/ListDocumentGenerator.php" size="6695" time="2022-03-18T17:20:59+00:00" unixtime="1647624059" sha1="ae57fcdf8640e7ee0363414bd02389f980a40653" relative="ar/www/html/vendor/friendsofphp/php-cs-fixer/src/Documentation/ListDocumentGenerator.php"/>
  <docblock>
    <description/>
    <internal/>
  </docblock>
  <member name="locator" visibility="private" static="false" line="33"/>
  <constructor name="__construct" start="35" end="38" abstract="false" final="false" static="false" visibility="public">
    <parameter name="locator" byreference="false" type="object">
      <type full="PhpCsFixer\Documentation\DocumentationLocator" namespace="PhpCsFixer\Documentation" name="DocumentationLocator"/>
    </parameter>
  </constructor>
  <method name="generateListingDocumentation" start="43" end="175" abstract="false" final="false" static="false" visibility="public">
    <docblock>
      <description/>
      <param type="array" variable="$fixers" of="object">
        <type full="PhpCsFixer\Documentation\FixerInterface" namespace="PhpCsFixer\Documentation" name="FixerInterface"/>
      </param>
    </docblock>
    <return type="string" nullable="false"/>
    <parameter name="fixers" byreference="false" type="array"/>
  </method>
</class>
