<?xml version="1.0" encoding="UTF-8"?>
<class xmlns="http://xml.phpdox.net/src" full="SlevomatCodingStandard\Helpers\Annotation\TypeAliasAnnotation" namespace="SlevomatCodingStandard\Helpers\Annotation" name="TypeAliasAnnotation" abstract="false" final="false" start="15" end="67">
  <file path="//var/www/html/vendor/slevomat/coding-standard/SlevomatCodingStandard/Helpers/Annotation" file="TypeAliasAnnotation.php" realpath="/var/www/html/vendor/slevomat/coding-standard/SlevomatCodingStandard/Helpers/Annotation/TypeAliasAnnotation.php" size="1463" time="2022-03-29T12:44:16+00:00" unixtime="1648557856" sha1="ffcf999c9a77c44a7b628c5befe7903a9266a0e2" relative="ar/www/html/vendor/slevomat/coding-standard/SlevomatCodingStandard/Helpers/Annotation/TypeAliasAnnotation.php"/>
  <docblock>
    <description/>
    <internal/>
  </docblock>
  <extends full="SlevomatCodingStandard\Helpers\Annotation\Annotation" namespace="SlevomatCodingStandard\Helpers\Annotation" name="Annotation"/>
  <member name="contentNode" visibility="private" static="false" line="19">
    <docblock>
      <var type="object">
        <type full="SlevomatCodingStandard\Helpers\Annotation\TypeAliasTagValueNode|null" namespace="SlevomatCodingStandard\Helpers\Annotation" name="TypeAliasTagValueNode|null"/>
      </var>
    </docblock>
  </member>
  <constructor name="__construct" start="21" end="34" abstract="false" final="false" static="false" visibility="public">
    <parameter name="name" byreference="false" type="string"/>
    <parameter name="startPointer" byreference="false" type="int"/>
    <parameter name="endPointer" byreference="false" type="int"/>
    <parameter name="content" byreference="false" nullable="true" type="string"/>
    <parameter name="contentNode" byreference="false" nullable="true" type="object">
      <type full="PHPStan\PhpDocParser\Ast\PhpDoc\TypeAliasTagValueNode" namespace="PHPStan\PhpDocParser\Ast\PhpDoc" name="TypeAliasTagValueNode"/>
    </parameter>
  </constructor>
  <method name="isInvalid" start="36" end="39" abstract="false" final="false" static="false" visibility="public">
    <return type="bool" nullable="false"/>
  </method>
  <method name="getContentNode" start="41" end="46" abstract="false" final="false" static="false" visibility="public">
    <return type="object" nullable="false">
      <type full="PHPStan\PhpDocParser\Ast\PhpDoc\TypeAliasTagValueNode" namespace="PHPStan\PhpDocParser\Ast\PhpDoc" name="TypeAliasTagValueNode"/>
    </return>
  </method>
  <method name="getAlias" start="48" end="53" abstract="false" final="false" static="false" visibility="public">
    <return type="string" nullable="false"/>
  </method>
  <method name="getType" start="55" end="60" abstract="false" final="false" static="false" visibility="public">
    <return type="object" nullable="false">
      <type full="PHPStan\PhpDocParser\Ast\Type\TypeNode" namespace="PHPStan\PhpDocParser\Ast\Type" name="TypeNode"/>
    </return>
  </method>
  <method name="export" start="62" end="65" abstract="false" final="false" static="false" visibility="public">
    <return type="string" nullable="false"/>
  </method>
  <parent full="SlevomatCodingStandard\Helpers\Annotation\Annotation" namespace="SlevomatCodingStandard\Helpers\Annotation" name="Annotation">
    <member name="name" visibility="protected" static="false" line="17">
      <docblock>
        <var type="string"/>
      </docblock>
    </member>
    <member name="startPointer" visibility="protected" static="false" line="20">
      <docblock>
        <var type="int"/>
      </docblock>
    </member>
    <member name="endPointer" visibility="protected" static="false" line="23">
      <docblock>
        <var type="int"/>
      </docblock>
    </member>
    <member name="content" visibility="protected" static="false" line="26">
      <docblock>
        <var type="object">
          <type full="SlevomatCodingStandard\Helpers\Annotation\string|null" namespace="SlevomatCodingStandard\Helpers\Annotation" name="string|null"/>
        </var>
      </docblock>
    </member>
    <method name="isInvalid" start="28" end="28" abstract="true" final="false" static="false" visibility="public">
      <return type="bool" nullable="false"/>
    </method>
    <method name="export" start="30" end="30" abstract="true" final="false" static="false" visibility="public">
      <return type="string" nullable="false"/>
    </method>
    <constructor name="__construct" start="32" end="38" abstract="false" final="false" static="false" visibility="public">
      <parameter name="name" byreference="false" type="string"/>
      <parameter name="startPointer" byreference="false" type="int"/>
      <parameter name="endPointer" byreference="false" type="int"/>
      <parameter name="content" byreference="false" nullable="true" type="string"/>
    </constructor>
    <method name="getName" start="40" end="43" abstract="false" final="false" static="false" visibility="public">
      <return type="string" nullable="false"/>
    </method>
    <method name="getStartPointer" start="45" end="48" abstract="false" final="false" static="false" visibility="public">
      <return type="int" nullable="false"/>
    </method>
    <method name="getEndPointer" start="50" end="53" abstract="false" final="false" static="false" visibility="public">
      <return type="int" nullable="false"/>
    </method>
    <method name="getContent" start="55" end="58" abstract="false" final="false" static="false" visibility="public">
      <return type="string" nullable="true"/>
    </method>
    <method name="fixDescription" start="60" end="63" abstract="false" final="false" static="false" visibility="protected">
      <return type="string" nullable="false"/>
      <parameter name="description" byreference="false" type="string"/>
    </method>
    <method name="errorWhenInvalid" start="65" end="70" abstract="false" final="false" static="false" visibility="protected">
      <return type="void" nullable="false"/>
    </method>
  </parent>
</class>
