<?xml version="1.0" encoding="UTF-8"?>
<class xmlns="http://xml.phpdox.net/src" full="Symfony\Component\Cache\DependencyInjection\CachePoolPass" namespace="Symfony\Component\Cache\DependencyInjection" name="CachePoolPass" abstract="false" final="false" start="30" end="274">
  <file path="//var/www/html/vendor/symfony/cache/DependencyInjection" file="CachePoolPass.php" realpath="/var/www/html/vendor/symfony/cache/DependencyInjection/CachePoolPass.php" size="11729" time="2022-04-26T13:19:20+00:00" unixtime="1650979160" sha1="82004cd2ae17d3ddf9eb25b9d2785618f871eabf" relative="ar/www/html/vendor/symfony/cache/DependencyInjection/CachePoolPass.php"/>
  <docblock>
    <description/>
    <author value="Nicolas Grekas &lt;p@tchwork.com&gt;"/>
  </docblock>
  <implements full="Symfony\Component\DependencyInjection\Compiler\CompilerPassInterface" namespace="Symfony\Component\DependencyInjection\Compiler" name="CompilerPassInterface" unresolved="true"/>
  <member name="cachePoolTag" visibility="private" static="false" line="32"/>
  <member name="kernelResetTag" visibility="private" static="false" line="33"/>
  <member name="cacheClearerId" visibility="private" static="false" line="34"/>
  <member name="cachePoolClearerTag" visibility="private" static="false" line="35"/>
  <member name="cacheSystemClearerId" visibility="private" static="false" line="36"/>
  <member name="cacheSystemClearerTag" visibility="private" static="false" line="37"/>
  <member name="reverseContainerId" visibility="private" static="false" line="38"/>
  <member name="reversibleTag" visibility="private" static="false" line="39"/>
  <member name="messageHandlerId" visibility="private" static="false" line="40"/>
  <constructor name="__construct" start="42" end="57" abstract="false" final="false" static="false" visibility="public">
    <parameter name="cachePoolTag" byreference="false" type="string" default="'cache.pool'"/>
    <parameter name="kernelResetTag" byreference="false" type="string" default="'kernel.reset'"/>
    <parameter name="cacheClearerId" byreference="false" type="string" default="'cache.global_clearer'"/>
    <parameter name="cachePoolClearerTag" byreference="false" type="string" default="'cache.pool.clearer'"/>
    <parameter name="cacheSystemClearerId" byreference="false" type="string" default="'cache.system_clearer'"/>
    <parameter name="cacheSystemClearerTag" byreference="false" type="string" default="'kernel.cache_clearer'"/>
    <parameter name="reverseContainerId" byreference="false" type="string" default="'reverse_container'"/>
    <parameter name="reversibleTag" byreference="false" type="string" default="'container.reversible'"/>
    <parameter name="messageHandlerId" byreference="false" type="string" default="'cache.early_expiration_handler'"/>
  </constructor>
  <method name="process" start="62" end="246" abstract="false" final="false" static="false" visibility="public">
    <docblock>
      <description compact="{@inheritdoc}"/>
    </docblock>
    <parameter name="container" byreference="false" type="object">
      <type full="Symfony\Component\DependencyInjection\ContainerBuilder" namespace="Symfony\Component\DependencyInjection" name="ContainerBuilder"/>
    </parameter>
  </method>
  <method name="getNamespace" start="248" end="251" abstract="false" final="false" static="false" visibility="private">
    <parameter name="seed" byreference="false" type="string"/>
    <parameter name="id" byreference="false" type="string"/>
  </method>
  <method name="getServiceProvider" start="256" end="273" abstract="false" final="false" static="true" visibility="public">
    <docblock>
      <description/>
      <internal/>
    </docblock>
    <parameter name="container" byreference="false" type="object">
      <type full="Symfony\Component\DependencyInjection\ContainerBuilder" namespace="Symfony\Component\DependencyInjection" name="ContainerBuilder"/>
    </parameter>
    <parameter name="name" byreference="false" type="string"/>
  </method>
</class>
